odoo/addons/website_event_filter_city/README.rst
odoo/addons/website_event_filter_city/__init__.py
odoo/addons/website_event_filter_city/__manifest__.py
odoo/addons/website_event_filter_city/controllers/__init__.py
odoo/addons/website_event_filter_city/controllers/main.py
odoo/addons/website_event_filter_city/demo/assets.xml
odoo/addons/website_event_filter_city/demo/tour_data.xml
odoo/addons/website_event_filter_city/i18n/de.po
odoo/addons/website_event_filter_city/i18n/es.po
odoo/addons/website_event_filter_city/i18n/website_event_filter_city.pot
odoo/addons/website_event_filter_city/i18n/website_event_filter_selector.pot
odoo/addons/website_event_filter_city/models/__init__.py
odoo/addons/website_event_filter_city/models/event.py
odoo/addons/website_event_filter_city/readme/CONFIGURE.rst
odoo/addons/website_event_filter_city/readme/CONTRIBUTORS.rst
odoo/addons/website_event_filter_city/readme/DESCRIPTION.rst
odoo/addons/website_event_filter_city/readme/ROADMAP.rst
odoo/addons/website_event_filter_city/static/description/all.png
odoo/addons/website_event_filter_city/static/description/icon.png
odoo/addons/website_event_filter_city/static/description/index.html
odoo/addons/website_event_filter_city/static/src/js/website_event_filter_city.tour.js
odoo/addons/website_event_filter_city/templates/event.xml
odoo/addons/website_event_filter_city/tests/__init__.py
odoo/addons/website_event_filter_city/tests/test_ui.py
odoo13_addon_website_event_filter_city-13.0.1.0.2.dist-info/METADATA
odoo13_addon_website_event_filter_city-13.0.1.0.2.dist-info/WHEEL
odoo13_addon_website_event_filter_city-13.0.1.0.2.dist-info/top_level.txt
odoo13_addon_website_event_filter_city-13.0.1.0.2.dist-info/RECORD
