Metadata-Version: 2.1
Name: odoo13-addon-website-event-filter-city
Version: 13.0.1.0.2
Summary: Add a customizable top area to filter events with city
Home-page: https://github.com/OCA/event
Author: Antiun Ingeniería S.L., Tecnativa, Onestein, Odoo Community Association (OCA)
Author-email: support@odoo-community.org
License: LGPL-3
Platform: UNKNOWN
Classifier: Programming Language :: Python
Classifier: Framework :: Odoo
Classifier: Framework :: Odoo :: 13.0
Classifier: License :: OSI Approved :: GNU Lesser General Public License v3 (LGPLv3)
Requires-Python: >=3.5
Requires-Dist: odoo (<13.1dev,>=13.0a)
